app_configuration/__init__.py
app_configuration/app_configuration.py
app_configuration/core/__init__.py
app_configuration/core/base_request.py
app_configuration/core/constants.py
app_configuration/core/internal/__init__.py
app_configuration/core/internal/api_exception.py
app_configuration/core/internal/base_response.py
app_configuration/core/internal/logger.py
app_configuration/core/internal/utils.py
app_configuration/feature/__init__.py
app_configuration/feature/feature_handler.py
app_configuration/feature/internal/__init__.py
app_configuration/feature/internal/utils/__init__.py
app_configuration/feature/internal/utils/file_manager.py
app_configuration/feature/internal/utils/metering.py
app_configuration/feature/internal/utils/socket.py
app_configuration/feature/internal/utils/url_builder.py
app_configuration/feature/internal/utils/validators.py
app_configuration/feature/models/__init__.py
app_configuration/feature/models/feature.py
app_configuration/feature/models/rule.py
app_configuration/feature/models/segment.py
app_configuration/feature/models/segment_rules.py
examples/__init__.py
examples/sample_app.py
examples/server_sample.py
ibm_appconfiguration/__init__.py
ibm_appconfiguration/appconfiguration.py
ibm_appconfiguration/core/__init__.py
ibm_appconfiguration/core/base_request.py
ibm_appconfiguration/core/internal/__init__.py
ibm_appconfiguration/core/internal/api_exception.py
ibm_appconfiguration/core/internal/base_response.py
ibm_appconfiguration/core/internal/logger.py
ibm_appconfiguration/core/internal/utils.py
ibm_appconfiguration/feature/__init__.py
ibm_appconfiguration/feature/feature_handler.py
ibm_appconfiguration/feature/internal/__init__.py
ibm_appconfiguration/feature/internal/common/__init__.py
ibm_appconfiguration/feature/internal/common/constants.py
ibm_appconfiguration/feature/internal/utils/__init__.py
ibm_appconfiguration/feature/internal/utils/file_manager.py
ibm_appconfiguration/feature/internal/utils/metering.py
srikanth_test_python_sdk-1.0.1.dist-info/LICENSE
srikanth_test_python_sdk-1.0.1.dist-info/METADATA
srikanth_test_python_sdk-1.0.1.dist-info/WHEEL
srikanth_test_python_sdk-1.0.1.dist-info/top_level.txt
srikanth_test_python_sdk-1.0.1.dist-info/RECORD
