Metadata-Version: 2.1
Name: srikanth-test-python-sdk
Version: 1.0.1
Summary: Python server SDK
Home-page: https://github.com/IBM/appconfiguration-python-sdk
Author: ME
Author-email: kms100@gmail.com
License: Apache 2.0
Keywords: python,ibm_appconfiguration
Platform: UNKNOWN
Classifier: Development Status :: 5 - Production/Stable
Classifier: License :: OSI Approved :: Apache Software License
Classifier: Programming Language :: Python :: 3
Requires-Python: >=3.0
Requires-Dist: python-dateutil (>=2.8)
Requires-Dist: requests (<3.0,>=2.20)
Requires-Dist: websocket-client (==0.48.0)
